pnwcybersec/__init__.py
pnwcybersec/pnwcybersec.py
pnwcybersec-0.1.3.dist-info/LICENSE.TXT
pnwcybersec-0.1.3.dist-info/METADATA
pnwcybersec-0.1.3.dist-info/WHEEL
pnwcybersec-0.1.3.dist-info/top_level.txt
pnwcybersec-0.1.3.dist-info/RECORD
