Metadata-Version: 2.1
Name: pnwcybersec
Version: 0.1.3
Summary: A deep learning malware detection module.
Home-page: https://github.com/bbdcmf/pnwcybersec
Author: Ryan Frederick, Joseph Shapiro
Author-email: freder20@pnw.edu
License: Apache License 2.0
Project-URL: Bug Tracker, https://github.com/bbdcmf/pnwcybersec/issues
Keywords: Deep Learning,Cyber Security
Platform: UNKNOWN
Classifier: Development Status :: 3 - Alpha
Classifier: Intended Audience :: Education
Classifier: License :: OSI Approved :: Apache Software License
Classifier: Natural Language :: English
Classifier: Operating System :: OS Independent
Classifier: Programming Language :: Python :: 2.7
Classifier: Programming Language :: Python :: 3.6
Classifier: Programming Language :: Python :: 3.7
License-File: LICENSE.TXT
Requires-Dist: fastai
Requires-Dist: pandas
Requires-Dist: numpy
Requires-Dist: pillow
Requires-Dist: matplotlib
